{
  "source": "trends",
  "topic_id": "portable-anxiety-relief",
  "fetched_at": "2026-02-25T07:11:47.061001Z",
  "items": [
    {
      "id": "portable-anxiety-relief:iot:anxiety necklace review",
      "text": "TRENDS: interest over time average (14d) for 'anxiety necklace review' is 0.0",
      "timestamp": "2026-02-25T07:11:45.165003Z",
      "lang": "en"
    },
    {
      "id": "portable-anxiety-relief:iot:breathing necklace review problems",
      "text": "TRENDS: interest over time average (14d) for 'breathing necklace review problems' is 0.0",
      "timestamp": "2026-02-25T07:11:45.756284Z",
      "lang": "en"
    }
  ]
}